toascii/__init__.py
toascii/cli.py
toascii/converters/__init__.py
toascii/converters/base_converter.py
toascii/converters/color_converter.py
toascii/converters/extensions/color_converter.nim
toascii/converters/extensions/color_converter_nim.py
toascii/converters/extensions/converter_utils.nim
toascii/converters/extensions/extension_utils.py
toascii/converters/extensions/grayscale_converter.nim
toascii/converters/extensions/grayscale_converter_nim.py
toascii/converters/extensions/html_color_converter.nim
toascii/converters/extensions/html_color_converter_nim.py
toascii/converters/extensions/nim.cfg
toascii/converters/extensions/nimpy_numpy.nim
toascii/converters/extensions/unsupported_extension.py
toascii/converters/grayscale_converter.py
toascii/converters/html_color_converter.py
toascii/converters/options.py
toascii/gradients.py
toascii/image.py
toascii/media_source.py
toascii/video.py
to_ascii-6.1.0.dist-info/LICENSE
to_ascii-6.1.0.dist-info/METADATA
to_ascii-6.1.0.dist-info/WHEEL
to_ascii-6.1.0.dist-info/entry_points.txt
to_ascii-6.1.0.dist-info/RECORD
