Metadata-Version: 2.1
Name: to-ascii
Version: 6.1.0
Summary: Convert videos, images, gifs, and even live video to ASCII art!
Home-page: https://github.com/Iapetus-11/To-ASCII
License: MIT
Keywords: ascii,color,colors,ascii-art,video,image,nim
Author: Milo Weinberg
Author-email: iapetus011@gmail.com
Requires-Python: >=3.9,<4.0
Classifier: License :: OSI Approved :: MIT License
Classifier: Programming Language :: Python :: 3
Classifier: Programming Language :: Python :: 3.9
Classifier: Programming Language :: Python :: 3.10
Classifier: Programming Language :: Python :: 3.11
Provides-Extra: cli
Provides-Extra: speedups
Requires-Dist: click (>=8.1.8,<9.0.0) ; extra == "cli"
Requires-Dist: colorama (>=0.4.6,<0.5.0)
Requires-Dist: nimporter (>=1.1.0,<2.0.0) ; extra == "speedups"
Requires-Dist: numpy (==2.0)
Requires-Dist: opencv-python (>=4.10.0.84,<5.0.0.0)
Requires-Dist: pydantic (>=1.9.1,<2.0.0)
Project-URL: Repository, https://github.com/Iapetus-11/To-ASCII
